{
  "generatedAt": "2026-04-27T20:36:45.930Z",
  "date": "16-03-2026",
  "count": 1,
  "summary": null,
  "items": [
    {
      "id": "hf_paper_2604.16353",
      "title": "AgriIR: A Scalable Framework for Domain-Specific Knowledge Retrieval",
      "url": "https://huggingface.co/papers/2604.16353",
      "source": "HuggingFace Papers",
      "sourceIcon": "🤗",
      "type": "research",
      "timestamp": "2026-03-16T20:00:00.000Z",
      "abstract": "This paper introduces AgriIR, a configurable retrieval augmented generation (RAG) framework designed to deliver grounded, domain-specific answers while maintaining flexibility and low computational co",
      "authors": [
        "Shuvam Banerji Seal",
        "Aheli Poddar",
        "Alok Mishra",
        "Dwaipayan Roy"
      ],
      "tags": [],
      "score": 6,
      "priority": "MEDIUM",
      "sentiment": "neutral",
      "downloads": 0,
      "likes": 0,
      "stars": 0,
      "votes": 0,
      "points": 0
    }
  ]
}