{
  "generatedAt": "2026-05-20T19:14:18.697Z",
  "date": "01-05-2026",
  "count": 1,
  "summary": null,
  "items": [
    {
      "id": "google_research_https%3A%2F%2Fresearch.google%2Fblog%2Fc",
      "title": "Catalyzing scientific impact through global partnerships and open resources",
      "url": "https://research.google/blog/catalyzing-scientific-impact-through-global-partnerships-and-open-resources/",
      "source": "Google Research",
      "sourceIcon": "🔍",
      "type": "research",
      "timestamp": "2026-05-01T16:37:00.000Z",
      "abstract": "Data Mining &amp; Modeling",
      "authors": [],
      "tags": [],
      "score": 4,
      "priority": "LOW",
      "sentiment": "neutral",
      "downloads": 0,
      "likes": 0,
      "stars": 0,
      "votes": 0,
      "points": 0
    }
  ]
}