{
  "generatedAt": "2026-06-02T20:51:26.527Z",
  "date": "25-05-2026",
  "count": 1,
  "summary": null,
  "items": [
    {
      "id": "hf_paper_2605.09156",
      "title": "Lost in Translation? Exploring the Shift in Grammatical Gender from Latin to Occitan",
      "url": "https://huggingface.co/papers/2605.09156",
      "source": "HuggingFace Papers",
      "sourceIcon": "🤗",
      "type": "research",
      "timestamp": "2026-05-25T20:00:00.000Z",
      "abstract": "The diachronic evolution from Latin to the Romance languages involved a restructuring of the grammatical gender system from a tripartite configuration (masculine, feminine, neuter) to a bipartite one",
      "authors": [
        "Ahan Chatterjee",
        "Matthias Schöffel",
        "Matthias Aßenmacher",
        "Marinus Wiedner",
        "Esteban Garces Arias"
      ],
      "tags": [],
      "score": 6,
      "priority": "MEDIUM",
      "sentiment": "neutral",
      "downloads": 0,
      "likes": 0,
      "stars": 0,
      "votes": 0,
      "points": 0
    }
  ]
}