{
  "generatedAt": "2026-06-08T13:48:00.187Z",
  "date": "29-05-2026",
  "count": 2,
  "summary": null,
  "items": [
    {
      "id": "hf_paper_2606.00590",
      "title": "Critic-R: Improving Agentic Search using Instruction-tuned Retrievers with Natural Language Introspective Feedback",
      "url": "https://huggingface.co/papers/2606.00590",
      "source": "HuggingFace Papers",
      "sourceIcon": "🤗",
      "type": "research",
      "timestamp": "2026-05-29T20:00:00.000Z",
      "abstract": "Agentic search systems iteratively interact with retrieval models to answer complex queries. Despite substantial progress, optimizing retrievers for agentic search remains challenging, often requiring",
      "authors": [
        "Md Zarif Ul Alam",
        "Alireza Salemi",
        "Hamed Zamani"
      ],
      "tags": [
        "agent"
      ],
      "score": 6,
      "priority": "MEDIUM",
      "sentiment": "neutral",
      "downloads": 0,
      "likes": 0,
      "stars": 0,
      "votes": 0,
      "points": 0
    },
    {
      "id": "mit_tech_review_https%3A%2F%2Fwww.technologyreview.com%2",
      "title": "How the Pope’s Magnifica Humanitas offers a template for individuals to meet the AI moment",
      "url": "https://www.technologyreview.com/2026/05/29/1138107/how-the-popes-magnifica-humanitas-offers-a-template-for-individuals-to-meet-the-ai-moment/",
      "source": "MIT Tech Review",
      "sourceIcon": "🏛️",
      "type": "research",
      "timestamp": "2026-05-29T10:00:00.000Z",
      "abstract": "",
      "authors": [],
      "tags": [],
      "score": 4,
      "priority": "LOW",
      "sentiment": "neutral",
      "downloads": 0,
      "likes": 0,
      "stars": 0,
      "votes": 0,
      "points": 0
    }
  ]
}