{
  "generatedAt": "2026-04-09T20:53:23.135Z",
  "date": "04-04-2026",
  "count": 2,
  "summary": null,
  "items": [
    {
      "id": "hf_paper_2604.04247",
      "title": "Combee: Scaling Prompt Learning for Self-Improving Language Model Agents",
      "url": "https://huggingface.co/papers/2604.04247",
      "source": "HuggingFace Papers",
      "sourceIcon": "🤗",
      "type": "research",
      "timestamp": "2026-04-04T20:00:00.000Z",
      "abstract": "Recent advances in prompt learning allow large language model agents to acquire task-relevant knowledge from inference-time context without parameter changes. For example, existing methods (like ACE o",
      "authors": [
        "Hanchen Li",
        "Runyuan He",
        "Qizheng Zhang",
        "Changxiu Ji",
        "Qiuyang Mang"
      ],
      "tags": [
        "agent"
      ],
      "score": 6,
      "priority": "MEDIUM",
      "sentiment": "neutral",
      "downloads": 0,
      "likes": 0,
      "stars": 0,
      "votes": 0,
      "points": 0
    },
    {
      "id": "hf_paper_2604.03995",
      "title": "A Systematic Study of Cross-Modal Typographic Attacks on Audio-Visual Reasoning",
      "url": "https://huggingface.co/papers/2604.03995",
      "source": "HuggingFace Papers",
      "sourceIcon": "🤗",
      "type": "research",
      "timestamp": "2026-04-04T20:00:00.000Z",
      "abstract": "As audio-visual multi-modal large language models (MLLMs) are increasingly deployed in safety-critical applications, understanding their vulnerabilities is crucial. To this end, we introduce Multi-Mod",
      "authors": [
        "Tianle Chen",
        "Deepti Ghadiyaram"
      ],
      "tags": [
        "phi"
      ],
      "score": 6,
      "priority": "MEDIUM",
      "sentiment": "neutral",
      "downloads": 0,
      "likes": 0,
      "stars": 0,
      "votes": 0,
      "points": 0
    }
  ]
}