{
  "generatedAt": "2026-04-18T10:32:42.831Z",
  "date": "12-04-2026",
  "count": 2,
  "summary": null,
  "items": [
    {
      "id": "hf_paper_2604.11707",
      "title": "Representations Before Pixels: Semantics-Guided Hierarchical Video Prediction",
      "url": "https://huggingface.co/papers/2604.11707",
      "source": "HuggingFace Papers",
      "sourceIcon": "🤗",
      "type": "research",
      "timestamp": "2026-04-12T20:00:00.000Z",
      "abstract": "Accurate future video prediction requires both high visual fidelity and consistent scene semantics, particularly in complex dynamic environments such as autonomous driving. We present Re2Pix, a hierar",
      "authors": [
        "Efstathios Karypidis",
        "Spyros Gidaris",
        "Nikos Komodakis"
      ],
      "tags": [],
      "score": 6,
      "priority": "MEDIUM",
      "sentiment": "neutral",
      "downloads": 0,
      "likes": 0,
      "stars": 0,
      "votes": 0,
      "points": 0
    },
    {
      "id": "nvidia_blog_https%3A%2F%2Fdeveloper.nvidia.com%2Fblo",
      "title": "MiniMax M2.7 Advances Scalable Agentic Workflows on NVIDIA Platforms for Complex AI Applications",
      "url": "https://developer.nvidia.com/blog/minimax-m2-7-advances-scalable-agentic-workflows-on-nvidia-platforms-for-complex-ai-applications/",
      "source": "NVIDIA Blog",
      "sourceIcon": "🟩",
      "type": "tool",
      "timestamp": "2026-04-12T01:02:44.000Z",
      "abstract": "The release of&nbsp;MiniMax M2.7&nbsp;adds enhancements to the popular&nbsp;MiniMax&nbsp;M2.5 model,&nbsp;built for agentic harnesses,...]]>",
      "authors": [],
      "tags": [
        "agent"
      ],
      "score": 8,
      "priority": "HIGH",
      "sentiment": "positive",
      "downloads": 0,
      "likes": 0,
      "stars": 0,
      "votes": 0,
      "points": 0
    }
  ]
}